[{"id":1,"first_name":"Antonio","last_name":"Carpenter","email":"acarpenter0@cbsnews.com","gender":"Male","address":"4 American Center","city":"Delray Beach","state":"FL","zip":"33448"},
{"id":2,"first_name":"Walter","last_name":"Chavez","email":"wchavez1@china.com.cn","gender":"Male","address":"54023 Bluestem Terrace","city":"Philadelphia","state":"PA","zip":"19184"},
{"id":3,"first_name":"Louis","last_name":"Cook","email":"lcook2@imgur.com","gender":"Male","address":"16358 Mayfield Park","city":"Duluth","state":"GA","zip":"30096"},
{"id":4,"first_name":"Michael","last_name":"Burton","email":"mburton3@jalbum.net","gender":"Male","address":"9 Kings Parkway","city":"San Diego","state":"CA","zip":"92127"},
{"id":5,"first_name":"Nancy","last_name":"Castillo","email":"ncastillo4@cnn.com","gender":"Female","address":"3868 Laurel Terrace","city":"Fort Worth","state":"TX","zip":"76178"},
{"id":6,"first_name":"Betty","last_name":"Porter","email":"bporter5@dagondesign.com","gender":"Female","address":"9 Cottonwood Way","city":"Washington","state":"DC","zip":"20299"},
{"id":7,"first_name":"Kevin","last_name":"Nguyen","email":"knguyen6@istockphoto.com","gender":"Male","address":"87337 Arapahoe Place","city":"Evansville","state":"IN","zip":"47719"},
{"id":8,"first_name":"Shawn","last_name":"Jones","email":"sjones7@whitehouse.gov","gender":"Male","address":"351 Brentwood Pass","city":"Providence","state":"RI","zip":"02912"},
{"id":9,"first_name":"Lillian","last_name":"Peters","email":"lpeters8@globo.com","gender":"Female","address":"428 Orin Way","city":"Washington","state":"DC","zip":"20016"},
{"id":10,"first_name":"Norma","last_name":"Knight","email":"nknight9@wisc.edu","gender":"Female","address":"50470 Lillian Drive","city":"El Paso","state":"TX","zip":"88584"},
{"id":11,"first_name":"Laura","last_name":"Nelson","email":"lnelsona@1und1.de","gender":"Female","address":"401 Blaine Alley","city":"Denver","state":"CO","zip":"80279"},
{"id":12,"first_name":"Angela","last_name":"Watkins","email":"awatkinsb@si.edu","gender":"Female","address":"28381 Bluejay Trail","city":"Jacksonville","state":"FL","zip":"32236"},
{"id":13,"first_name":"Paula","last_name":"Nelson","email":"pnelsonc@icio.us","gender":"Female","address":"9101 Glendale Parkway","city":"Lynchburg","state":"VA","zip":"24503"},
{"id":14,"first_name":"Stephen","last_name":"Mitchell","email":"smitchelld@vk.com","gender":"Male","address":"88 Alpine Lane","city":"Burbank","state":"CA","zip":"91520"},
{"id":15,"first_name":"Melissa","last_name":"Ward","email":"mwarde@ucla.edu","gender":"Female","address":"0456 Sachs Park","city":"Inglewood","state":"CA","zip":"90305"},
{"id":16,"first_name":"Judith","last_name":"Perry","email":"jperryf@feedburner.com","gender":"Female","address":"40 Park Meadow Alley","city":"Lake Worth","state":"FL","zip":"33467"},
{"id":17,"first_name":"Virginia","last_name":"Harris","email":"vharrisg@phoca.cz","gender":"Female","address":"5358 Kipling Park","city":"Topeka","state":"KS","zip":"66617"},
{"id":18,"first_name":"Kathy","last_name":"Kelly","email":"kkellyh@miibeian.gov.cn","gender":"Female","address":"3643 Morning Park","city":"Chicago","state":"IL","zip":"60641"},
{"id":19,"first_name":"Amanda","last_name":"Fox","email":"afoxi@booking.com","gender":"Female","address":"2 Brentwood Trail","city":"Erie","state":"PA","zip":"16565"},
{"id":20,"first_name":"Donald","last_name":"Carpenter","email":"dcarpenterj@privacy.gov.au","gender":"Male","address":"844 Shasta Hill","city":"Wichita","state":"KS","zip":"67260"},
{"id":21,"first_name":"Edward","last_name":"Ryan","email":"eryank@sogou.com","gender":"Male","address":"40456 Lien Park","city":"Saint Augustine","state":"FL","zip":"32092"},
{"id":22,"first_name":"Rachel","last_name":"Kim","email":"rkiml@behance.net","gender":"Female","address":"397 Gale Hill","city":"Monticello","state":"MN","zip":"55590"},
{"id":23,"first_name":"Carl","last_name":"Harvey","email":"charveym@ovh.net","gender":"Male","address":"1 School Court","city":"Springfield","state":"VA","zip":"22156"},
{"id":24,"first_name":"Denise","last_name":"Watkins","email":"dwatkinsn@ox.ac.uk","gender":"Female","address":"52 Haas Court","city":"Boca Raton","state":"FL","zip":"33487"},
{"id":25,"first_name":"Howard","last_name":"Hamilton","email":"hhamiltono@tumblr.com","gender":"Male","address":"15 Gina Park","city":"Detroit","state":"MI","zip":"48211"},
{"id":26,"first_name":"Christine","last_name":"Austin","email":"caustinp@washingtonpost.com","gender":"Female","address":"56 Welch Avenue","city":"Farmington","state":"MI","zip":"48335"},
{"id":27,"first_name":"Richard","last_name":"Ray","email":"rrayq@springer.com","gender":"Male","address":"44690 Parkside Avenue","city":"Akron","state":"OH","zip":"44315"},
{"id":28,"first_name":"Theresa","last_name":"Nguyen","email":"tnguyenr@examiner.com","gender":"Female","address":"50 Bartelt Court","city":"Chattanooga","state":"TN","zip":"37410"},
{"id":29,"first_name":"John","last_name":"Mitchell","email":"jmitchells@ow.ly","gender":"Male","address":"97 Kensington Point","city":"Vero Beach","state":"FL","zip":"32969"},
{"id":30,"first_name":"Jessica","last_name":"Webb","email":"jwebbt@photobucket.com","gender":"Female","address":"25332 Golden Leaf Street","city":"Yonkers","state":"NY","zip":"10705"},
{"id":31,"first_name":"Thomas","last_name":"Reynolds","email":"treynoldsu@admin.ch","gender":"Male","address":"683 Petterle Drive","city":"Saint Louis","state":"MO","zip":"63110"},
{"id":32,"first_name":"Timothy","last_name":"Day","email":"tdayv@vkontakte.ru","gender":"Male","address":"307 Independence Terrace","city":"Birmingham","state":"AL","zip":"35254"},
{"id":33,"first_name":"Mary","last_name":"Murphy","email":"mmurphyw@baidu.com","gender":"Female","address":"7544 Graedel Way","city":"Trenton","state":"NJ","zip":"08608"},
{"id":34,"first_name":"Mildred","last_name":"Harper","email":"mharperx@trellian.com","gender":"Female","address":"1 Ruskin Center","city":"Dallas","state":"TX","zip":"75246"},
{"id":35,"first_name":"Donna","last_name":"Carr","email":"dcarry@icq.com","gender":"Female","address":"972 Shoshone Hill","city":"Pittsburgh","state":"PA","zip":"15205"},
{"id":36,"first_name":"Christopher","last_name":"Wilson","email":"cwilsonz@dion.ne.jp","gender":"Male","address":"1 Heath Road","city":"Amarillo","state":"TX","zip":"79118"},
{"id":37,"first_name":"Pamela","last_name":"Miller","email":"pmiller10@cargocollective.com","gender":"Female","address":"87331 Kenwood Avenue","city":"Dallas","state":"TX","zip":"75226"},
{"id":38,"first_name":"Nicholas","last_name":"Nelson","email":"nnelson11@google.co.jp","gender":"Male","address":"280 Drewry Hill","city":"Pasadena","state":"CA","zip":"91186"},
{"id":39,"first_name":"Jessica","last_name":"Cunningham","email":"jcunningham12@army.mil","gender":"Female","address":"2606 1st Court","city":"Washington","state":"DC","zip":"20409"},
{"id":40,"first_name":"Frank","last_name":"Elliott","email":"felliott13@alexa.com","gender":"Male","address":"5572 Fremont Alley","city":"Birmingham","state":"AL","zip":"35290"},
{"id":41,"first_name":"Roger","last_name":"Lane","email":"rlane14@pbs.org","gender":"Male","address":"79 Crownhardt Terrace","city":"Clearwater","state":"FL","zip":"34615"},
{"id":42,"first_name":"Laura","last_name":"Perkins","email":"lperkins15@omniture.com","gender":"Female","address":"81 Grasskamp Drive","city":"Manchester","state":"NH","zip":"03105"},
{"id":43,"first_name":"Steve","last_name":"Turner","email":"sturner16@digg.com","gender":"Male","address":"26 Spenser Terrace","city":"Saint Paul","state":"MN","zip":"55108"},
{"id":44,"first_name":"Michael","last_name":"Hart","email":"mhart17@webnode.com","gender":"Male","address":"4078 7th Court","city":"Washington","state":"DC","zip":"20210"},
{"id":45,"first_name":"Robert","last_name":"Dunn","email":"rdunn18@facebook.com","gender":"Male","address":"4 Morningstar Crossing","city":"Anchorage","state":"AK","zip":"99599"},
{"id":46,"first_name":"Nicholas","last_name":"Watson","email":"nwatson19@cbslocal.com","gender":"Male","address":"958 Burrows Plaza","city":"New York City","state":"NY","zip":"10034"},
{"id":47,"first_name":"Frances","last_name":"Coleman","email":"fcoleman1a@deviantart.com","gender":"Female","address":"43 Maple Wood Drive","city":"Santa Clara","state":"CA","zip":"95054"},
{"id":48,"first_name":"Raymond","last_name":"Hansen","email":"rhansen1b@unblog.fr","gender":"Male","address":"28 Orin Way","city":"San Francisco","state":"CA","zip":"94142"},
{"id":49,"first_name":"Juan","last_name":"Watson","email":"jwatson1c@noaa.gov","gender":"Male","address":"2915 Graceland Alley","city":"Washington","state":"DC","zip":"20005"},
{"id":50,"first_name":"Robert","last_name":"Oliver","email":"roliver1d@un.org","gender":"Male","address":"7 Glendale Circle","city":"Washington","state":"DC","zip":"20036"},
{"id":51,"first_name":"Diane","last_name":"Ross","email":"dross1e@ustream.tv","gender":"Female","address":"0 Gale Way","city":"Tyler","state":"TX","zip":"75705"},
{"id":52,"first_name":"Antonio","last_name":"Martin","email":"amartin1f@si.edu","gender":"Male","address":"075 Haas Pass","city":"Seattle","state":"WA","zip":"98127"},
{"id":53,"first_name":"Jack","last_name":"Porter","email":"jporter1g@yellowpages.com","gender":"Male","address":"442 Armistice Circle","city":"Fort Wayne","state":"IN","zip":"46825"},
{"id":54,"first_name":"Kevin","last_name":"Woods","email":"kwoods1h@chronoengine.com","gender":"Male","address":"1951 Lillian Junction","city":"College Station","state":"TX","zip":"77844"},
{"id":55,"first_name":"Stephen","last_name":"Gibson","email":"sgibson1i@jiathis.com","gender":"Male","address":"8 Clyde Gallagher Circle","city":"Houston","state":"TX","zip":"77045"},
{"id":56,"first_name":"Harold","last_name":"Kennedy","email":"hkennedy1j@utexas.edu","gender":"Male","address":"523 Jenna Plaza","city":"Jersey City","state":"NJ","zip":"07305"},
{"id":57,"first_name":"Albert","last_name":"Miller","email":"amiller1k@photobucket.com","gender":"Male","address":"16 Crescent Oaks Alley","city":"Des Moines","state":"IA","zip":"50393"},
{"id":58,"first_name":"Richard","last_name":"Fowler","email":"rfowler1l@theatlantic.com","gender":"Male","address":"190 Burning Wood Drive","city":"Norfolk","state":"VA","zip":"23514"},
{"id":59,"first_name":"Kenneth","last_name":"Ford","email":"kford1m@geocities.jp","gender":"Male","address":"9 Transport Lane","city":"Houston","state":"TX","zip":"77065"},
{"id":60,"first_name":"Albert","last_name":"Mason","email":"amason1n@imdb.com","gender":"Male","address":"8 Truax Court","city":"Portland","state":"OR","zip":"97229"},
{"id":61,"first_name":"Judith","last_name":"Ellis","email":"jellis1o@noaa.gov","gender":"Female","address":"21048 Crescent Oaks Way","city":"Albuquerque","state":"NM","zip":"87121"},
{"id":62,"first_name":"Emily","last_name":"Gray","email":"egray1p@ox.ac.uk","gender":"Female","address":"1991 Pankratz Road","city":"Richmond","state":"VA","zip":"23225"},
{"id":63,"first_name":"Jeffrey","last_name":"Armstrong","email":"jarmstrong1q@oakley.com","gender":"Male","address":"2 Roth Circle","city":"Roanoke","state":"VA","zip":"24040"},
{"id":64,"first_name":"Brian","last_name":"Oliver","email":"boliver1r@princeton.edu","gender":"Male","address":"3 Dennis Point","city":"Rockford","state":"IL","zip":"61110"},
{"id":65,"first_name":"Carol","last_name":"Hicks","email":"chicks1s@edublogs.org","gender":"Female","address":"84 Golf Drive","city":"Decatur","state":"GA","zip":"30089"},
{"id":66,"first_name":"Stephen","last_name":"Hudson","email":"shudson1t@wp.com","gender":"Male","address":"64974 Vernon Pass","city":"Saint Louis","state":"MO","zip":"63180"},
{"id":67,"first_name":"Jacqueline","last_name":"King","email":"jking1u@omniture.com","gender":"Female","address":"7 Mallard Center","city":"Salt Lake City","state":"UT","zip":"84110"},
{"id":68,"first_name":"Jerry","last_name":"Gibson","email":"jgibson1v@state.gov","gender":"Male","address":"83 Mcguire Park","city":"Boise","state":"ID","zip":"83757"},
{"id":69,"first_name":"Rachel","last_name":"Richards","email":"rrichards1w@berkeley.edu","gender":"Female","address":"80128 Stuart Way","city":"Saint Augustine","state":"FL","zip":"32092"},
{"id":70,"first_name":"George","last_name":"Weaver","email":"gweaver1x@europa.eu","gender":"Male","address":"82137 Forster Terrace","city":"Springfield","state":"MO","zip":"65805"},
{"id":71,"first_name":"Douglas","last_name":"George","email":"dgeorge1y@usatoday.com","gender":"Male","address":"2133 Forster Drive","city":"San Antonio","state":"TX","zip":"78260"},
{"id":72,"first_name":"Mark","last_name":"Meyer","email":"mmeyer1z@free.fr","gender":"Male","address":"62 Heath Place","city":"Mesa","state":"AZ","zip":"85215"},
{"id":73,"first_name":"Daniel","last_name":"Gordon","email":"dgordon20@economist.com","gender":"Male","address":"98 Loomis Park","city":"Memphis","state":"TN","zip":"38136"},
{"id":74,"first_name":"Victor","last_name":"Vasquez","email":"vvasquez21@ihg.com","gender":"Male","address":"0213 Rockefeller Terrace","city":"Dearborn","state":"MI","zip":"48126"},
{"id":75,"first_name":"Stephen","last_name":"Franklin","email":"sfranklin22@cnbc.com","gender":"Male","address":"6621 Russell Plaza","city":"Corpus Christi","state":"TX","zip":"78410"},
{"id":76,"first_name":"Beverly","last_name":"Berry","email":"bberry23@answers.com","gender":"Female","address":"497 Ramsey Parkway","city":"Ocala","state":"FL","zip":"34474"},
{"id":77,"first_name":"Eric","last_name":"Fields","email":"efields24@bloglines.com","gender":"Male","address":"344 Hermina Street","city":"Largo","state":"FL","zip":"34643"},
{"id":78,"first_name":"Pamela","last_name":"Owens","email":"powens25@unc.edu","gender":"Female","address":"27693 Buell Trail","city":"Miami","state":"FL","zip":"33134"},
{"id":79,"first_name":"Debra","last_name":"Hunt","email":"dhunt26@elpais.com","gender":"Female","address":"8 Marcy Terrace","city":"Amarillo","state":"TX","zip":"79188"},
{"id":80,"first_name":"Christine","last_name":"Hart","email":"chart27@odnoklassniki.ru","gender":"Female","address":"93096 Schlimgen Street","city":"Reno","state":"NV","zip":"89505"},
{"id":81,"first_name":"Victor","last_name":"Gilbert","email":"vgilbert28@cbsnews.com","gender":"Male","address":"58 Manley Circle","city":"Vienna","state":"VA","zip":"22184"},
{"id":82,"first_name":"Ryan","last_name":"Daniels","email":"rdaniels29@spotify.com","gender":"Male","address":"33 Morning Court","city":"Spring","state":"TX","zip":"77388"},
{"id":83,"first_name":"Christopher","last_name":"Griffin","email":"cgriffin2a@cloudflare.com","gender":"Male","address":"6 Esch Place","city":"Carson City","state":"NV","zip":"89714"},
{"id":84,"first_name":"Ronald","last_name":"Richards","email":"rrichards2b@twitter.com","gender":"Male","address":"28386 Birchwood Terrace","city":"Saint Paul","state":"MN","zip":"55127"},
{"id":85,"first_name":"Jimmy","last_name":"Lopez","email":"jlopez2c@multiply.com","gender":"Male","address":"562 Hermina Alley","city":"Pompano Beach","state":"FL","zip":"33075"},
{"id":86,"first_name":"Judy","last_name":"Bell","email":"jbell2d@newsvine.com","gender":"Female","address":"7928 Wayridge Point","city":"Tucson","state":"AZ","zip":"85732"},
{"id":87,"first_name":"Katherine","last_name":"Wagner","email":"kwagner2e@eventbrite.com","gender":"Female","address":"5 Green Ridge Pass","city":"Fargo","state":"ND","zip":"58122"},
{"id":88,"first_name":"Robin","last_name":"Morales","email":"rmorales2f@google.ru","gender":"Female","address":"1236 Ohio Alley","city":"Washington","state":"DC","zip":"20078"},
{"id":89,"first_name":"Carol","last_name":"Duncan","email":"cduncan2g@gravatar.com","gender":"Female","address":"1 Mcguire Place","city":"Birmingham","state":"AL","zip":"35205"},
{"id":90,"first_name":"Brian","last_name":"Clark","email":"bclark2h@cam.ac.uk","gender":"Male","address":"051 Anhalt Terrace","city":"Buffalo","state":"NY","zip":"14215"},
{"id":91,"first_name":"Barbara","last_name":"Fox","email":"bfox2i@google.com.br","gender":"Female","address":"6604 Sauthoff Way","city":"Philadelphia","state":"PA","zip":"19146"},
{"id":92,"first_name":"Chris","last_name":"Baker","email":"cbaker2j@webmd.com","gender":"Male","address":"8101 Pankratz Drive","city":"Trenton","state":"NJ","zip":"08608"},
{"id":93,"first_name":"Louise","last_name":"Porter","email":"lporter2k@mozilla.org","gender":"Female","address":"8 Mallory Drive","city":"Minneapolis","state":"MN","zip":"55441"},
{"id":94,"first_name":"George","last_name":"Garcia","email":"ggarcia2l@sciencedaily.com","gender":"Male","address":"1875 Transport Road","city":"Pensacola","state":"FL","zip":"32575"},
{"id":95,"first_name":"Benjamin","last_name":"Price","email":"bprice2m@slashdot.org","gender":"Male","address":"1 Lindbergh Circle","city":"Lynn","state":"MA","zip":"01905"},
{"id":96,"first_name":"Patricia","last_name":"Alexander","email":"palexander2n@mapy.cz","gender":"Female","address":"42 Myrtle Parkway","city":"Syracuse","state":"NY","zip":"13251"},
{"id":97,"first_name":"Maria","last_name":"Chavez","email":"mchavez2o@alibaba.com","gender":"Female","address":"448 High Crossing Way","city":"Portland","state":"OR","zip":"97211"},
{"id":98,"first_name":"Matthew","last_name":"Berry","email":"mberry2p@naver.com","gender":"Male","address":"0 Atwood Pass","city":"Marietta","state":"GA","zip":"30066"},
{"id":99,"first_name":"Joe","last_name":"Hanson","email":"jhanson2q@163.com","gender":"Male","address":"70588 Mendota Place","city":"Reston","state":"VA","zip":"20195"},
{"id":100,"first_name":"Louise","last_name":"Olson","email":"lolson2r@php.net","gender":"Female","address":"20148 Caliangt Pass","city":"Fresno","state":"CA","zip":"93721"}]